README.txt
setup.py
collective/__init__.py
collective.beancounter.egg-info/PKG-INFO
collective.beancounter.egg-info/SOURCES.txt
collective.beancounter.egg-info/dependency_links.txt
collective.beancounter.egg-info/entry_points.txt
collective.beancounter.egg-info/namespace_packages.txt
collective.beancounter.egg-info/not-zip-safe
collective.beancounter.egg-info/paster_plugins.txt
collective.beancounter.egg-info/requires.txt
collective.beancounter.egg-info/top_level.txt
collective/beancounter/README.txt
collective/beancounter/__init__.py
collective/beancounter/adapter.py
collective/beancounter/configure.zcml
collective/beancounter/interfaces.py
collective/beancounter/tests.py
collective/beancounter/browser/__init__.py
docs/HISTORY.txt
docs/INSTALL.txt
docs/LICENSE.GPL
docs/LICENSE.txt
