Metadata-Version: 1.0
Name: collective.beancounter
Version: 0.2
Summary: package to display a fill-percentage for AT based content
Home-page: https://svn.plone.org/svn/collective/collective.beancounter/trunk
Author: Stefan Eletzhofer
Author-email: stefan.eletzhofer@inquant.de
License: GPL
Platform: UNKNOWN
Classifier: Framework :: Plone
Classifier: Framework :: Zope2
Classifier: Framework :: Zope3
Classifier: Programming Language :: Python
Classifier: Topic :: Software Development :: Libraries :: Python Modules
